mwr_raw2l1/__init__.py
mwr_raw2l1/__main__.py
mwr_raw2l1/config/L1_format.yaml
mwr_raw2l1/config/config_0-20000-0-06610_A.yaml
mwr_raw2l1/config/config_0-20000-0-06620_A.yaml
mwr_raw2l1/config/config_0-20000-0-10393_A.yaml
mwr_raw2l1/config/config_0-20000-0-99999_A.yaml
mwr_raw2l1/config/config_0-20008-0-IZO_A.yaml
mwr_raw2l1/config/log_config.yaml
mwr_raw2l1/config/qc_config.yaml
mwr_raw2l1/data/.gitignore
mwr_raw2l1/data/attex/0-20000-0-99999/MWR_0-20000-0-99999_A20211107.tbr
mwr_raw2l1/data/attex/0-20000-0-99999/MWR_0-20000-0-99999_A20211108.tbr
mwr_raw2l1/data/radiometrics/0-20000-0-10393/MWR_0-20000-0-10393_A202101310004_lv0.csv
mwr_raw2l1/data/radiometrics/0-20000-0-10393/MWR_0-20000-0-10393_A202101310004_lv1.csv
mwr_raw2l1/data/radiometrics/0-20000-0-10393/MWR_0-20000-0-10393_A202101310004_tip.csv
mwr_raw2l1/data/rpg/0-20000-0-06610/MWR_0-20000-0-06610_A201908040100.BLB
mwr_raw2l1/data/rpg/0-20000-0-06610/MWR_0-20000-0-06610_A201908040100.BRT
mwr_raw2l1/data/rpg/0-20000-0-06610/MWR_0-20000-0-06610_A201908040100.HKD
mwr_raw2l1/data/rpg/0-20000-0-06610/MWR_0-20000-0-06610_A201908040100.IRT
mwr_raw2l1/data/rpg/0-20000-0-06610/MWR_0-20000-0-06610_A201908040100.MET
mwr_raw2l1/data/rpg/0-20000-0-06610/MWR_0-20000-0-06610_A201908050100.BLB
mwr_raw2l1/data/rpg/0-20000-0-06610/MWR_0-20000-0-06610_A201908050100.BRT
mwr_raw2l1/data/rpg/0-20000-0-06610/MWR_0-20000-0-06610_A201908050100.HKD
mwr_raw2l1/data/rpg/0-20000-0-06610/MWR_0-20000-0-06610_A201908050100.IRT
mwr_raw2l1/data/rpg/0-20000-0-06610/MWR_0-20000-0-06610_A201908050100.MET
mwr_raw2l1/data/rpg/0-20000-0-06620/MWR_0-20000-0-06620_A202305182353.BRT
mwr_raw2l1/data/rpg/0-20000-0-06620/MWR_0-20000-0-06620_A202305182353.HKD
mwr_raw2l1/data/rpg/0-20000-0-06620/MWR_0-20000-0-06620_A202305182353.MET
mwr_raw2l1/data/rpg/0-20000-0-06620/MWR_0-20000-0-06620_A202305182358.BRT
mwr_raw2l1/data/rpg/0-20000-0-06620/MWR_0-20000-0-06620_A202305182358.HKD
mwr_raw2l1/data/rpg/0-20000-0-06620/MWR_0-20000-0-06620_A202305182358.MET
mwr_raw2l1-1.0.0.dist-info/entry_points.txt
mwr_raw2l1-1.0.0.dist-info/LICENSE
mwr_raw2l1-1.0.0.dist-info/WHEEL
mwr_raw2l1-1.0.0.dist-info/METADATA
mwr_raw2l1-1.0.0.dist-info/RECORD
